{"coNumber":{"0":1,"1":2,"2":3,"3":4,"4":1,"5":2,"6":3,"7":4},"coTitle":{"0":"Interpret the need for advanced Java concepts like enumerations and collections in developing modular and efficient programs","1":"Demonstrate various String Handling Mechanism","2":"Describe how servlets fit into Java-based web application architecture","3":"Illustrate database access and details for managing information using the JDBC API","4":"Interpret the need for advanced Java concepts like enumerations and collections in developing modular and efficient programs","5":"Demonstrate various String Handling Mechanism","6":"Describe how servlets fit into Java-based web application architecture","7":"Illustrate database access and details for managing information using the JDBC API"},"termNumber":{"0":"5","1":"5","2":"5","3":"5","4":"5","5":"5","6":"5","7":"5"},"section":{"0":"A","1":"A","2":"A","3":"A","4":"B","5":"B","6":"B","7":"B"},"courseCode":{"0":"15CS553","1":"15CS553","2":"15CS553","3":"15CS553","4":"15CS553","5":"15CS553","6":"15CS553","7":"15CS553"},"year":{"0":"2018-19","1":"2018-19","2":"2018-19","3":"2018-19","4":"2018-19","5":"2018-19","6":"2018-19","7":"2018-19"},"facultyId":{"0":"465","1":"465","2":"465","3":"465","4":"465","5":"465","6":"465","7":"465"},"dir_methodName":{"0":["IA","UE","Other Assessment"],"1":["IA","UE","Other Assessment"],"2":["IA","UE","Other Assessment"],"3":["IA","UE","Other Assessment"],"4":["IA","UE","Other Assessment"],"5":["IA","UE","Other Assessment"],"6":["IA","UE","Other Assessment"],"7":["IA","UE","Other Assessment"]},"dir_methodDescription":{"0":["Internal Assessment",""],"1":["Internal Assessment",""],"2":["Internal Assessment",""],"3":["Internal Assessment",""],"4":["Internal Assessment",""],"5":["Internal Assessment",""],"6":["Internal Assessment",""],"7":["Internal Assessment",""]},"dir_attainment":{"0":[87.2425758467,70.4545454545,86.1909795631],"1":[85.6574074074,70.4545454545,96.9696969697],"2":[88.0892658067,70.4545454545,0.0],"3":[88.9527458493,70.4545454545,0.0],"4":[90.5269947761,71.4285714286,91.7328042328],"5":[89.604759024,71.4285714286,97.2222222222],"6":[96.9438470729,71.4285714286,0.0],"7":[93.3333333333,71.4285714286,0.0]},"dir_attainmentPercentage":{"0":[0.0,0.0,0.0],"1":[0.0,0.0,0.0],"2":[0.0,0.0,0.0],"3":[0.0,0.0,0.0],"4":[0.0,0.0,0.0],"5":[0.0,0.0,0.0],"6":[0.0,0.0,0.0],"7":[0.0,0.0,0.0]},"indir_attainment":{"0":[88.8888888889],"1":[88.8888888889],"2":[88.8888888889],"3":[88.8888888889],"4":[100.0],"5":[100.0],"6":[100.0],"7":[100.0]},"indir_attainmentPercentage":{"0":[0.0],"1":[0.0],"2":[0.0],"3":[0.0],"4":[0.0],"5":[0.0],"6":[0.0],"7":[0.0]},"indir_methodName":{"0":["Feedback"],"1":["Feedback"],"2":["Feedback"],"3":["Feedback"],"4":["Feedback"],"5":["Feedback"],"6":["Feedback"],"7":["Feedback"]},"indir_methodDescription":{"0":["CES"],"1":["CES"],"2":["CES"],"3":["CES"],"4":["CES"],"5":["CES"],"6":["CES"],"7":["CES"]},"totalAttainment":{"0":79.4294561642,"1":79.9113131313,"2":72.7373833896,"3":72.9446185998,"4":83.3508173706,"5":83.5686342293,"6":77.5522375832,"7":76.6857142857},"directAttainment":{"0":77.064597983,"1":77.6669191919,"2":68.6995070147,"3":68.9585510275,"4":79.1885217133,"5":79.4607927866,"6":71.940296979,"7":70.8571428571},"indirectAttainment":{"0":88.8888888889,"1":88.8888888889,"2":88.8888888889,"3":88.8888888889,"4":100.0,"5":100.0,"6":100.0,"7":100.0}}